pocketsizefund/__init__.py
pocketsizefund/config.py
pocketsizefund/data.py
pocketsizefund/model.py
pocketsizefund/storage.py
pocketsizefund/trade.py
pocketsizefund-20240831.0.dist-info/METADATA
pocketsizefund-20240831.0.dist-info/WHEEL
pocketsizefund-20240831.0.dist-info/RECORD
