Metadata-Version: 2.3
Name: pocketsizefund
Version: 20240831.0
Summary: Open source quantitative trading
Author-email: forstmeier <john.forstmeier@gmail.com>, chrisaddy <chris.william.addy@gmail.com>
License: MIT
Requires-Python: <3.11,>=3.9
Requires-Dist: alpaca-py>=0.30.1
Requires-Dist: boto3>=1.35.10
Requires-Dist: bs4>=0.0.2
Requires-Dist: loguru>=0.7.2
Requires-Dist: pandas>=2.2.2
Requires-Dist: requests>=2.32.3
Requires-Dist: wandb>=0.17.8
Provides-Extra: ml
Requires-Dist: pytorch-forecasting; extra == 'ml'
Provides-Extra: trade
Requires-Dist: alpaca-py; extra == 'trade'
